wolfx_client/__init__.py
wolfx_client/client.py
wolfx_client/types/EEW.py
wolfx_client/types/EQL.py
wolfx_client/types/heartbeat.py
wolfx_client-1.1.1.dist-info/licenses/LICENSE
wolfx_client-1.1.1.dist-info/METADATA
wolfx_client-1.1.1.dist-info/WHEEL
wolfx_client-1.1.1.dist-info/top_level.txt
wolfx_client-1.1.1.dist-info/RECORD
