Metadata-Version: 2.4
Name: Wolfx_Client
Version: 1.1.1
Summary: A WebSocket client for WolfX
Home-page: https://github.com/aic-6301/wolfx_client
Author: AIC_6301
Author-email: hello@aisii.net
Classifier: Development Status :: 5 - Production/Stable
Classifier: Intended Audience :: Developers
Classifier: License :: OSI Approved :: MIT License
Classifier: Programming Language :: Python :: 3.12
Classifier: Framework :: AsyncIO
License-File: LICENSE
Requires-Dist: websockets
Requires-Dist: asyncio
Dynamic: author
Dynamic: author-email
Dynamic: classifier
Dynamic: description
Dynamic: description-content-type
Dynamic: home-page
Dynamic: license-file
Dynamic: requires-dist
Dynamic: summary
